LICENSE
README.md
pyproject.toml
setup.py
src/mlops_forge/__init__.py
src/mlops_forge.egg-info/PKG-INFO
src/mlops_forge.egg-info/SOURCES.txt
src/mlops_forge.egg-info/dependency_links.txt
src/mlops_forge.egg-info/top_level.txt
src/mlops_forge/api/__init__.py
src/mlops_forge/api/api.py
src/mlops_forge/api/schemas.py
src/mlops_forge/cli/__init__.py
src/mlops_forge/config/__init__.py
src/mlops_forge/config/settings.py
src/mlops_forge/data/__init__.py
src/mlops_forge/data/data_loader.py
src/mlops_forge/monitoring/__init__.py
src/mlops_forge/monitoring/ab_testing.py
src/mlops_forge/monitoring/drift_detection.py
src/mlops_forge/training/__init__.py
src/mlops_forge/training/distributed_trainer.py
src/mlops_forge/utils/__init__.py
src/mlops_forge/utils/logging_utils.py
src/mlops_production_system/__init__.py
src/mlops_production_system/api/__init__.py
src/mlops_production_system/api/api.py
src/mlops_production_system/api/schemas.py
src/mlops_production_system/cli/__init__.py
src/mlops_production_system/cli/monitor.py
src/mlops_production_system/cli/serve.py
src/mlops_production_system/cli/train.py
src/mlops_production_system/config/__init__.py
src/mlops_production_system/config/settings.py
src/mlops_production_system/data/__init__.py
src/mlops_production_system/data/data_loader.py
src/mlops_production_system/data/feature_engineering.py
src/mlops_production_system/models/__init__.py
src/mlops_production_system/models/model_trainer.py
src/mlops_production_system/monitoring/__init__.py
src/mlops_production_system/monitoring/ab_testing.py
src/mlops_production_system/monitoring/drift_detection.py
src/mlops_production_system/monitoring/metrics.py
src/mlops_production_system/monitoring/monitoring.py
src/mlops_production_system/pipeline/__init__.py
src/mlops_production_system/pipeline/training_pipeline.py
src/mlops_production_system/tracking/__init__.py
src/mlops_production_system/tracking/mlflow_extensions.py
src/mlops_production_system/training/__init__.py
src/mlops_production_system/training/distributed_trainer.py
src/mlops_production_system/utils/__init__.py
src/mlops_production_system/utils/logging_utils.py