Metadata-Version: 2.4
Name: mlops-forge
Version: 1.0.0
Summary: A complete production-ready MLOps framework with built-in distributed training, monitoring, and CI/CD.
Home-page: https://github.com/TaimoorKhan10/MLOps-Forge
Author: Taimoor Khan
Author-email: Taimoor Khan <contact@taimoorkhan.dev>
License-Expression: MIT
Project-URL: Homepage, https://github.com/TaimoorKhan10/MLOps-Forge
Project-URL: Bug Tracker, https://github.com/TaimoorKhan10/MLOps-Forge/issues
Classifier: Development Status :: 4 - Beta
Classifier: Programming Language :: Python :: 3
Classifier: Programming Language :: Python :: 3.9
Classifier: Programming Language :: Python :: 3.10
Classifier: Operating System :: OS Independent
Classifier: Topic :: Scientific/Engineering :: Artificial Intelligence
Classifier: Topic :: Software Development :: Libraries :: Application Frameworks
Requires-Python: >=3.9
License-File: LICENSE
Dynamic: author
Dynamic: home-page
Dynamic: license-file
Dynamic: requires-python
